dbt/__init__.py
dbt/adapters/__init__.py
dbt/adapters/oracle/__init__.py
dbt/adapters/oracle/connections.py
dbt/adapters/oracle/impl.py
dbt/adapters/oracle/relation.py
dbt/include/__init__.py
dbt/include/oracle/__init__.py
dbt/include/oracle/dbt_project.yml
dbt/include/oracle/macros/adapters.sql
dbt/include/oracle/macros/catalog.sql
dbt/include/oracle/macros/materializations/incremental.sql
dbt/include/oracle/macros/materializations/seed.sql
dbt/include/oracle/macros/materializations/snapshot.sql
dbt/include/oracle/macros/materializations/table.sql
dbt/include/oracle/macros/materializations/view.sql
dbt/include/oracle/macros/not_implemented.sql
dbt/include/oracle/macros/schema_tests.sql
dbt/include/oracle/macros/strategies.sql
dbt_oracledb-0.1.0.dist-info/WHEEL
dbt_oracledb-0.1.0.dist-info/METADATA
dbt_oracledb-0.1.0.dist-info/RECORD
