Metadata-Version: 2.1
Name: dbt-oracledb
Version: 0.1.0
Summary: DBT adapter for Oracle databases
Author: emacha
Author-email: 15370927+emacha@users.noreply.github.com
Requires-Python: >=3.8,<4.0
Classifier: Programming Language :: Python :: 3
Classifier: Programming Language :: Python :: 3.8
Classifier: Programming Language :: Python :: 3.9
Requires-Dist: cx-Oracle (>=8.1.0,<9.0.0)
Requires-Dist: dbt (>=0.19.0,<0.20.0)
